streamlit_admin/__init__.py
streamlit_admin/admin.py
streamlit_admin/model.py
streamlit_admin/stauth.py
streamlit_admin-0.1.1.dist-info/METADATA
streamlit_admin-0.1.1.dist-info/WHEEL
streamlit_admin-0.1.1.dist-info/top_level.txt
streamlit_admin-0.1.1.dist-info/RECORD
