Metadata-Version: 2.1
Name: streamlit-admin
Version: 0.1.1
Summary: Basic User Admin and Authenticator for Streamlit
Home-page: https://github.com/duducosmos/streamlit_admin
Author: Eduardo S. Pereira
Author-email: pereira.somoza@gmail.com
License: Apache License 2.0
Platform: UNKNOWN
Requires-Dist: bcrypt
Requires-Dist: pandas
Requires-Dist: pydal
Requires-Dist: streamlit
